{
  "_README": "Canonical gate metadata - source of truth for center, circuit, and channel assignments. DO NOT hardcode these mappings elsewhere.",
  "_SOURCES": [
    "Ra Uru Hu's Human Design System",
    "Jovian Archive official gate/center/circuit mappings",
    "Cross-referenced with multiple HD sources for accuracy"
  ],
  "gates": {
    "1":  { "center": "G",            "circuit_family": "Individual", "subcircuit": "Knowing",      "channel": "1-8" },
    "2":  { "center": "G",            "circuit_family": "Individual", "subcircuit": "Knowing",      "channel": "2-14" },
    "3":  { "center": "SACRAL",       "circuit_family": "Individual", "subcircuit": "Knowing",      "channel": "3-60" },
    "4":  { "center": "AJNA",         "circuit_family": "Collective", "subcircuit": "Understanding","channel": "4-63" },
    "5":  { "center": "SACRAL",       "circuit_family": "Collective", "subcircuit": "Understanding","channel": "5-15" },
    "6":  { "center": "SOLAR_PLEXUS", "circuit_family": "Tribal",     "subcircuit": "Defense",      "channel": "6-59" },
    "7":  { "center": "G",            "circuit_family": "Collective", "subcircuit": "Understanding","channel": "7-31" },
    "8":  { "center": "THROAT",       "circuit_family": "Individual", "subcircuit": "Knowing",      "channel": "1-8" },
    "9":  { "center": "SACRAL",       "circuit_family": "Collective", "subcircuit": "Understanding","channel": "9-52" },
    "10": { "center": "G",            "circuit_family": "Individual", "subcircuit": "Integration",  "channel": "10-20, 10-34, 10-57" },
    "11": { "center": "AJNA",         "circuit_family": "Collective", "subcircuit": "Sensing",      "channel": "11-56" },
    "12": { "center": "THROAT",       "circuit_family": "Individual", "subcircuit": "Knowing",      "channel": "12-22" },
    "13": { "center": "G",            "circuit_family": "Collective", "subcircuit": "Sensing",      "channel": "13-33" },
    "14": { "center": "SACRAL",       "circuit_family": "Individual", "subcircuit": "Knowing",      "channel": "2-14" },
    "15": { "center": "G",            "circuit_family": "Collective", "subcircuit": "Sensing",      "channel": "5-15" },
    "16": { "center": "THROAT",       "circuit_family": "Collective", "subcircuit": "Understanding","channel": "16-48" },
    "17": { "center": "AJNA",         "circuit_family": "Collective", "subcircuit": "Understanding","channel": "17-62" },
    "18": { "center": "SPLEEN",       "circuit_family": "Collective", "subcircuit": "Understanding","channel": "18-58" },
    "19": { "center": "ROOT",         "circuit_family": "Tribal",     "subcircuit": "Ego",          "channel": "19-49" },
    "20": { "center": "THROAT",       "circuit_family": "Individual", "subcircuit": "Integration",  "channel": "10-20, 20-34, 20-57" },
    "21": { "center": "EGO",          "circuit_family": "Tribal",     "subcircuit": "Ego",          "channel": "21-45" },
    "22": { "center": "SOLAR_PLEXUS", "circuit_family": "Individual", "subcircuit": "Knowing",      "channel": "12-22" },
    "23": { "center": "THROAT",       "circuit_family": "Individual", "subcircuit": "Knowing",      "channel": "23-43" },
    "24": { "center": "AJNA",         "circuit_family": "Individual", "subcircuit": "Knowing",      "channel": "24-61" },
    "25": { "center": "G",            "circuit_family": "Individual", "subcircuit": "Knowing",      "channel": "25-51" },
    "26": { "center": "EGO",          "circuit_family": "Tribal",     "subcircuit": "Ego",          "channel": "26-44" },
    "27": { "center": "SACRAL",       "circuit_family": "Tribal",     "subcircuit": "Defense",      "channel": "27-50" },
    "28": { "center": "SPLEEN",       "circuit_family": "Individual", "subcircuit": "Knowing",      "channel": "28-38" },
    "29": { "center": "SACRAL",       "circuit_family": "Collective", "subcircuit": "Sensing",      "channel": "29-46" },
    "30": { "center": "SOLAR_PLEXUS", "circuit_family": "Collective", "subcircuit": "Sensing",      "channel": "30-41" },
    "31": { "center": "THROAT",       "circuit_family": "Collective", "subcircuit": "Understanding","channel": "7-31" },
    "32": { "center": "SPLEEN",       "circuit_family": "Tribal",     "subcircuit": "Ego",          "channel": "32-54" },
    "33": { "center": "THROAT",       "circuit_family": "Collective", "subcircuit": "Sensing",      "channel": "13-33" },
    "34": { "center": "SACRAL",       "circuit_family": "Individual", "subcircuit": "Integration",  "channel": "10-34, 20-34" },
    "35": { "center": "THROAT",       "circuit_family": "Collective", "subcircuit": "Sensing",      "channel": "35-36" },
    "36": { "center": "SOLAR_PLEXUS", "circuit_family": "Collective", "subcircuit": "Sensing",      "channel": "35-36" },
    "37": { "center": "SOLAR_PLEXUS", "circuit_family": "Tribal",     "subcircuit": "Ego",          "channel": "37-40" },
    "38": { "center": "ROOT",         "circuit_family": "Individual", "subcircuit": "Knowing",      "channel": "28-38" },
    "39": { "center": "ROOT",         "circuit_family": "Individual", "subcircuit": "Knowing",      "channel": "39-55" },
    "40": { "center": "EGO",          "circuit_family": "Tribal",     "subcircuit": "Ego",          "channel": "37-40" },
    "41": { "center": "ROOT",         "circuit_family": "Collective", "subcircuit": "Sensing",      "channel": "30-41" },
    "42": { "center": "SACRAL",       "circuit_family": "Collective", "subcircuit": "Sensing",      "channel": "42-53" },
    "43": { "center": "AJNA",         "circuit_family": "Individual", "subcircuit": "Knowing",      "channel": "23-43" },
    "44": { "center": "SPLEEN",       "circuit_family": "Tribal",     "subcircuit": "Ego",          "channel": "26-44" },
    "45": { "center": "THROAT",       "circuit_family": "Tribal",     "subcircuit": "Ego",          "channel": "21-45" },
    "46": { "center": "G",            "circuit_family": "Collective", "subcircuit": "Sensing",      "channel": "29-46" },
    "47": { "center": "AJNA",         "circuit_family": "Collective", "subcircuit": "Sensing",      "channel": "47-64" },
    "48": { "center": "SPLEEN",       "circuit_family": "Collective", "subcircuit": "Understanding","channel": "16-48" },
    "49": { "center": "SOLAR_PLEXUS", "circuit_family": "Tribal",     "subcircuit": "Ego",          "channel": "19-49" },
    "50": { "center": "SPLEEN",       "circuit_family": "Tribal",     "subcircuit": "Defense",      "channel": "27-50" },
    "51": { "center": "EGO",          "circuit_family": "Individual", "subcircuit": "Knowing",      "channel": "25-51" },
    "52": { "center": "ROOT",         "circuit_family": "Collective", "subcircuit": "Understanding","channel": "9-52" },
    "53": { "center": "ROOT",         "circuit_family": "Collective", "subcircuit": "Sensing",      "channel": "42-53" },
    "54": { "center": "ROOT",         "circuit_family": "Tribal",     "subcircuit": "Ego",          "channel": "32-54" },
    "55": { "center": "SOLAR_PLEXUS", "circuit_family": "Individual", "subcircuit": "Knowing",      "channel": "39-55" },
    "56": { "center": "THROAT",       "circuit_family": "Collective", "subcircuit": "Sensing",      "channel": "11-56" },
    "57": { "center": "SPLEEN",       "circuit_family": "Individual", "subcircuit": "Integration",  "channel": "10-57, 20-57, 34-57" },
    "58": { "center": "ROOT",         "circuit_family": "Collective", "subcircuit": "Understanding","channel": "18-58" },
    "59": { "center": "SACRAL",       "circuit_family": "Tribal",     "subcircuit": "Defense",      "channel": "6-59" },
    "60": { "center": "ROOT",         "circuit_family": "Individual", "subcircuit": "Knowing",      "channel": "3-60" },
    "61": { "center": "HEAD",         "circuit_family": "Individual", "subcircuit": "Knowing",      "channel": "24-61" },
    "62": { "center": "THROAT",       "circuit_family": "Collective", "subcircuit": "Understanding","channel": "17-62" },
    "63": { "center": "HEAD",         "circuit_family": "Collective", "subcircuit": "Understanding","channel": "4-63" },
    "64": { "center": "HEAD",         "circuit_family": "Collective", "subcircuit": "Sensing",      "channel": "47-64" }
  }
}
